eiffellib/__init__.py
eiffellib/activity.py
eiffellib/events/__init__.py
eiffellib/events/eiffel_activity_canceled_event.py
eiffellib/events/eiffel_activity_finished_event.py
eiffellib/events/eiffel_activity_started_event.py
eiffellib/events/eiffel_activity_triggered_event.py
eiffellib/events/eiffel_announcement_published_event.py
eiffellib/events/eiffel_artifact_created_event.py
eiffellib/events/eiffel_artifact_published_event.py
eiffellib/events/eiffel_artifact_reused_event.py
eiffellib/events/eiffel_base_event.py
eiffellib/events/eiffel_composition_defined_event.py
eiffellib/events/eiffel_confidence_level_modified_event.py
eiffellib/events/eiffel_environment_defined_event.py
eiffellib/events/eiffel_flow_context_defined_event.py
eiffellib/events/eiffel_issue_defined_event.py
eiffellib/events/eiffel_issue_verified_event.py
eiffellib/events/eiffel_source_change_created_event.py
eiffellib/events/eiffel_source_change_submitted_event.py
eiffellib/events/eiffel_test_case_canceled_event.py
eiffellib/events/eiffel_test_case_finished_event.py
eiffellib/events/eiffel_test_case_started_event.py
eiffellib/events/eiffel_test_case_triggered_event.py
eiffellib/events/eiffel_test_execution_recipe_collection_created_event.py
eiffellib/events/eiffel_test_suite_finished_event.py
eiffellib/events/eiffel_test_suite_started_event.py
eiffellib/lib/__init__.py
eiffellib/lib/base_rabbitmq.py
eiffellib/publishers/__init__.py
eiffellib/publishers/eiffel_publisher.py
eiffellib/publishers/rabbitmq_publisher.py
eiffellib/schemas/EiffelActivityCanceledEvent/1.0.0.json
eiffellib/schemas/EiffelActivityCanceledEvent/1.1.0.json
eiffellib/schemas/EiffelActivityCanceledEvent/2.0.0.json
eiffellib/schemas/EiffelActivityCanceledEvent/3.0.0.json
eiffellib/schemas/EiffelActivityCanceledEvent/3.1.0.json
eiffellib/schemas/EiffelActivityCanceledEvent/3.2.0.json
eiffellib/schemas/EiffelActivityFinishedEvent/1.0.0.json
eiffellib/schemas/EiffelActivityFinishedEvent/1.1.0.json
eiffellib-3.0.0.dist-info/AUTHORS.rst
eiffellib-3.0.0.dist-info/LICENSE.txt
eiffellib-3.0.0.dist-info/METADATA
eiffellib-3.0.0.dist-info/WHEEL
eiffellib-3.0.0.dist-info/top_level.txt
eiffellib-3.0.0.dist-info/RECORD
